README.md
setup.py
algorithms/__init__.py
algorithms/collaborative_filtering/__init__.py
algorithms/collaborative_filtering/collaborative_filtering.py
algorithms/collaborative_filtering/matrix_factorization/__init__.py
algorithms/collaborative_filtering/matrix_factorization/matrix_factorization.py
algorithms/collaborative_filtering/matrix_factorization/stochastic_gradient_descent.py
algorithms/collaborative_filtering/matrix_factorization/explicit_feedback/__init__.py
algorithms/collaborative_filtering/matrix_factorization/explicit_feedback/matrix_factorization.py
algorithms/collaborative_filtering/matrix_factorization/explicit_feedback/matrix_factorization_prep.py
algorithms/collaborative_filtering/matrix_factorization/explicit_feedback/preprocess_matrix.py
algorithms/collaborative_filtering/matrix_factorization/implicit_feedback/__init__.py
algorithms/collaborative_filtering/matrix_factorization/implicit_feedback/matrix_factorization.py
algorithms/collaborative_filtering/neighborhood/__init__.py
algorithms/collaborative_filtering/neighborhood/clustering.py
algorithms/collaborative_filtering/neighborhood/item_clustering.py
algorithms/collaborative_filtering/neighborhood/item_neighborhood.py
algorithms/collaborative_filtering/neighborhood/neighborhood.py
algorithms/collaborative_filtering/neighborhood/user_based_cf.py
algorithms/collaborative_filtering/neighborhood/user_clustering.py
algorithms/collaborative_filtering/neighborhood/user_neighborhood.py
algorithms/collaborative_filtering/neighborhood/explicit_feedback/__init__.py
algorithms/collaborative_filtering/neighborhood/explicit_feedback/user_based/__init__.py
algorithms/collaborative_filtering/neighborhood/explicit_feedback/user_based/user_based_cf.py
algorithms/collaborative_filtering/neighborhood/explicit_feedback/user_based/user_based_clustering.py
algorithms/collaborative_filtering/neighborhood/explicit_feedback/user_based/user_based_neighborhood.py
increc.egg-info/PKG-INFO
increc.egg-info/SOURCES.txt
increc.egg-info/dependency_links.txt
increc.egg-info/top_level.txt
