Metadata-Version: 2.1
Name: increc
Version: 0.0.16
Summary: Software library on stream based recommender systems
Home-page: https://github.com/Marko50/FEUP-DISS
Author: Fernando André Fernandes
Author-email: fernandoandre49@gmail.com
License: UNKNOWN
Platform: UNKNOWN
Classifier: Programming Language :: Python :: 3
Classifier: License :: OSI Approved :: MIT License
Classifier: Operating System :: OS Independent
Requires-Python: >=3.7
